example/__init__.py
example/example.py
pyforms/__init__.py
pyforms/basewidget.py
pyforms/controls.py
pyforms/dialogs.py
pyforms/settings.py
pyforms_terminal/__init__.py
pyforms_terminal/allcontrols.py
pyforms_terminal/appmanager.py
pyforms_terminal/basewidget.py
pyforms_terminal/controls/__init__.py
pyforms_terminal/controls/control_base.py
pyforms_terminal/controls/control_boundingslider.py
pyforms_terminal/controls/control_button.py
pyforms_terminal/controls/control_checkbox.py
pyforms_terminal/controls/control_checkboxlist.py
pyforms_terminal/controls/control_combo.py
pyforms_terminal/controls/control_dir.py
pyforms_terminal/controls/control_emptywidget.py
pyforms_terminal/controls/control_file.py
pyforms_terminal/controls/control_image.py
pyforms_terminal/controls/control_label.py
pyforms_terminal/controls/control_list.py
pyforms_terminal/controls/control_matplotlib.py
pyforms_terminal/controls/control_number.py
pyforms_terminal/controls/control_player.py
pyforms_terminal/controls/control_progress.py
pyforms_terminal/controls/control_slider.py
pyforms_terminal/controls/control_text.py
pyforms_terminal/controls/control_textarea.py
pyforms_terminal/controls/control_toolbox.py
pyforms_terminal/controls/control_tree.py
pyforms_terminal/utils/BioradWriter.py
pyforms_terminal/utils/ImageBlobTools.py
pyforms_terminal/utils/__init__.py
pyforms_terminal/utils/make_lambda.py
pyforms_terminal/utils/plugins_finder.py
pyforms_terminal/utils/settings_manager.py
pyforms_terminal/utils/timeit.py
pyforms_terminal/utils/tools.py
PyForms_Terminal-4.0.10.dist-info/METADATA
PyForms_Terminal-4.0.10.dist-info/WHEEL
PyForms_Terminal-4.0.10.dist-info/top_level.txt
PyForms_Terminal-4.0.10.dist-info/RECORD
