Metadata-Version: 2.1
Name: PyForms-Terminal
Version: 4.0.10
Summary: Pyforms terminal is a software layer, part of the Pyforms main library. This layer implements the execution of a Pyforms application in the terminal.
Home-page: https://github.com/UmSenhorQualquer/pyforms-terminal
Author: Ricardo Ribeiro
Author-email: ricardojvr@gmail.com
License: MIT
Keywords: terminal development pyforms
Platform: UNKNOWN
Classifier: Development Status :: 5 - Production/Stable
Classifier: Topic :: Software Development :: Build Tools
Classifier: Programming Language :: Python :: 3
Classifier: Environment :: Console
Classifier: Intended Audience :: Developers
Classifier: Intended Audience :: End Users/Desktop
Classifier: Intended Audience :: Information Technology
Classifier: Intended Audience :: Science/Research
Classifier: Natural Language :: English
Classifier: Operating System :: MacOS :: MacOS X
Classifier: Operating System :: Microsoft :: Windows
Classifier: Operating System :: Unix
Classifier: Topic :: Scientific/Engineering :: Human Machine Interfaces
Classifier: Topic :: Software Development :: Libraries :: Application Frameworks
Classifier: Topic :: Software Development :: Libraries :: Python Modules
Requires-Python: >=3
Requires-Dist: requests
Requires-Dist: idna
Requires-Dist: simplejson
Requires-Dist: opencv-python (==3.4.5.20)
Requires-Dist: numpy
Requires-Dist: confapp
Requires-Dist: urllib3
Requires-Dist: Pillow
